{
	"pages": [{
		"path": "pages/home/home",
		"style": {
			"navigationBarTitleText": "uni-app"
		}
	}, {
		"path": "pages/account/account",
		"style": {
			"navigationBarTitleText": "uni-app"
		}
	}, {
		"path": "pages/account/account",
		"style": {
			"navigationBarTitleText": "",
			"enablePullDownRefresh": false
		}

	}, {
		"path": "pages/heart/heart",
		"style": {
			"navigationBarTitleText": "",
			"enablePullDownRefresh": false
		}

	}, {
		"path": "pages/plus/plus",
		"style": {
			"navigationBarTitleText": "",
			"enablePullDownRefresh": false
		}

	}, {
		"path": "pages/eye/eye",
		"style": {
			"navigationBarTitleText": "",
			"enablePullDownRefresh": false
		}

	}    ,{
            "path" : "pages/tagHome/tagHome",
            "style" :                                                                                    
            {
                "navigationBarTitleText": "",
                "enablePullDownRefresh": false
            }
            
        }
        ,{
            "path" : "pages/send-eye/send-eye",
            "style" :                                                                                    
            {
                "navigationBarTitleText": "",
                "enablePullDownRefresh": false
            }
            
        }
        ,{
            "path" : "pages/login/login",
            "style" :                                                                                    
            {
                "navigationBarTitleText": "",
                "enablePullDownRefresh": false
            }
            
        }
        ,{
            "path" : "pages/resigter/resigter",
            "style" :                                                                                    
            {
                "navigationBarTitleText": "",
                "enablePullDownRefresh": false
            }
            
        }
        ,{
            "path" : "pages/userInfo/userInfo",
            "style" :                                                                                    
            {
                "navigationBarTitleText": "",
                "enablePullDownRefresh": false
            }
            
        }
        ,{
            "path" : "pages/myPost/myPost",
            "style" :                                                                                    
            {
                "navigationBarTitleText": "",
                "enablePullDownRefresh": false
            }
            
        }
        ,{
            "path" : "pages/order/order",
            "style" :                                                                                    
            {
                "navigationBarTitleText": "",
                "enablePullDownRefresh": false
            }
            
        },{
            "path" : "pages/order/orderDetail",
            "style" :                                                                                    
            {
                "navigationBarTitleText": "",
                "enablePullDownRefresh": false
            }
            
        }
        ,{
            "path" : "pages/feedback/feedback",
            "style" :                                                                                    
            {
                "navigationBarTitleText": "",
                "enablePullDownRefresh": false
            }
            
        }
        ,{
            "path" : "pages/goodsDetail/goodsDetail",
            "style" :                                                                                    
            {
                "navigationBarTitleText": "",
                "enablePullDownRefresh": false
            }
            
        }
        ,{
            "path" : "pages/cart/cart",
            "style" :                                                                                    
            {
                "navigationBarTitleText": "",
                "enablePullDownRefresh": false
            }
            
        }
    ],
	"globalStyle": {
		"navigationBarTextStyle": "black",
		"navigationBarTitleText": "uni-app",
		"navigationBarBackgroundColor": "#F8F8F8",
		"backgroundColor": "#F8F8F8",
		"navigationStyle": "custom",
		"app-plus": {
			"background": "#efeff4"
		}
	},
	"easycom": {
		"^u-(.*)": "@/uni_modules/uview-ui/components/u-$1/u-$1.vue"
	}
}
